blue_form/__init__.py
blue_form-1.0.0.dist-info/METADATA
blue_form-1.0.0.dist-info/WHEEL
blue_form-1.0.0.dist-info/RECORD
