Metadata-Version: 2.1
Name: blue-form
Version: 1.0.0
Summary: Give you the blue form. A must have to get the 'Laisser-Passer A38'
Author: Tom Gabrièle
Author-email: tgabriele@alwaysdata.com
Requires-Python: >=3.11,<4.0
Classifier: Programming Language :: Python :: 3
Classifier: Programming Language :: Python :: 3.11
Requires-Dist: green-form (>=0.1.0,<0.2.0)
